wagtail_wordpress_import/__init__.py
wagtail_wordpress_import/analysis.py
wagtail_wordpress_import/apps.py
wagtail_wordpress_import/block_builder.py
wagtail_wordpress_import/block_builder_defaults.py
wagtail_wordpress_import/blocks.py
wagtail_wordpress_import/functions.py
wagtail_wordpress_import/handle_inline_shortcodes.py
wagtail_wordpress_import/logger.py
wagtail_wordpress_import/models.py
wagtail_wordpress_import/shortcodes.py
wagtail_wordpress_import/wagtail_hooks.py
wagtail_wordpress_import/xml_boilerplate.py
wagtail_wordpress_import/importers/__init__.py
wagtail_wordpress_import/importers/apps.py
wagtail_wordpress_import/importers/import_hooks.py
wagtail_wordpress_import/importers/wordpress.py
wagtail_wordpress_import/importers/wordpress_defaults.py
wagtail_wordpress_import/management/__init__.py
wagtail_wordpress_import/management/commands/__init__.py
wagtail_wordpress_import/management/commands/analyze_html_content.py
wagtail_wordpress_import/management/commands/analyze_xml_content.py
wagtail_wordpress_import/management/commands/delete_imported_pages.py
wagtail_wordpress_import/management/commands/import_xml.py
wagtail_wordpress_import/management/commands/reduce_xml.py
wagtail_wordpress_import/migrations/__init__.py
wagtail_wordpress_import/prefilters/__init__.py
wagtail_wordpress_import/prefilters/bleach_filter.py
wagtail_wordpress_import/prefilters/handle_shortcodes.py
wagtail_wordpress_import/prefilters/linebreaks_wp_filter.py
wagtail_wordpress_import/prefilters/transform_styles_defaults.py
wagtail_wordpress_import/prefilters/transform_styles_filter.py
wagtail_wordpress_import/static/wagtail_wordpress_import/js/.gitignore
wagtail_wordpress_import/static_src/custom.d.ts
wagtail_wordpress_import/static_src/main.tsx
wagtail_wordpress_import/templates/wagtail_wordpress_import/heading_block.html
wagtail_wordpress_import/templates/wagtail_wordpress_import/image_block.html
wagtail_wordpress_import/templates/wagtail_wordpress_import/quote_block.html
wagtail_wordpress_import-0.3.0.dist-info/LICENSE
wagtail_wordpress_import-0.3.0.dist-info/METADATA
wagtail_wordpress_import-0.3.0.dist-info/WHEEL
wagtail_wordpress_import-0.3.0.dist-info/top_level.txt
wagtail_wordpress_import-0.3.0.dist-info/RECORD
