Metadata-Version: 2.1
Name: wagtail-wordpress-import
Version: 0.3.0
Summary: Import XML data into wagtail to create pages and content
Home-page: https://github.com/torchbox/wagtail-wordpress-import
Author: Nick Moreton
Author-email: nickmoreton@me.com
License: BSD
Classifier: Intended Audience :: Developers
Classifier: License :: OSI Approved :: MIT License
Classifier: Programming Language :: Python
Classifier: Programming Language :: Python :: 3
Classifier: Programming Language :: Python :: 3.7
Classifier: Programming Language :: Python :: 3.8
Classifier: Programming Language :: Python :: 3.9
Classifier: Programming Language :: Python :: 3.10
Classifier: Framework :: Django
Classifier: Framework :: Django :: 3.1
Classifier: Framework :: Django :: 3.2
Classifier: Framework :: Django :: 4.0
Classifier: Framework :: Django :: 4.1
Classifier: Framework :: Wagtail
Classifier: Framework :: Wagtail :: 2
Classifier: Framework :: Wagtail :: 3
Classifier: Framework :: Wagtail :: 4
License-File: LICENSE
Requires-Dist: Django (>=3.2)
Requires-Dist: Wagtail (>=2.15)
Requires-Dist: lxml (<4.8,>=4.7)
Requires-Dist: bleach (<4.2,>=4.1)
Requires-Dist: prettytable (<2.3,>=2.2)
Requires-Dist: shortcodes (<6.0,>=5.1)
Requires-Dist: cached-property (<2.0,>=1.5.1)
Provides-Extra: testing
Requires-Dist: freezegun (==0.3.15) ; extra == 'testing'
Requires-Dist: responses (<0.17.0,>=0.16.0) ; extra == 'testing'
Requires-Dist: flake8 (==5.0.4) ; extra == 'testing'
Requires-Dist: isort (==5.10.1) ; extra == 'testing'
Requires-Dist: black (==22.10.0) ; extra == 'testing'
